{
  "Column": [
    {
      "schem": "dbo",
      "obj": "aspnet_Membership",
      "type": "Table",
      "name": "ApplicationId",
      "system_type_id": 36,
      "user_type_id": 36,
      "max_length": 16,
      "precision": 0,
      "scale": 0,
      "collation_name": null,
      "is_nullable": false,
      "is_ansi_padded": false,
      "is_rowguidcol": false,
      "is_identity": false,
      "is_computed": false,
      "is_filestream": false,
      "is_replicated": false,
      "is_non_sql_subscribed": false,
      "is_merge_published": false,
      "is_dts_replicated": false,
      "is_xml_document": false,
      "xml_collection_id": 0,
      "default_object_id": 0,
      "rule_object_id": 0,
      "is_sparse": false,
      "is_column_set": false,
      "generated_always_type": 0,
      "generated_always_type_desc": "NOT_APPLICABLE",
      "encryption_type": null,
      "encryption_type_desc": null,
      "encryption_algorithm_name": null,
      "column_encryption_key_id": null,
      "column_encryption_key_database_name": null,
      "is_hidden": false,
      "is_masked": false,
      "graph_type": null,
      "graph_type_desc": null
    },
    {
      "schem": "dbo",
      "obj": "aspnet_Membership",
      "type": "Table",
      "name": "UserId",
      "system_type_id": 36,
      "user_type_id": 36,
      "max_length": 16,
      "precision": 0,
      "scale": 0,
      "collation_name": null,
      "is_nullable": false,
      "is_ansi_padded": false,
      "is_rowguidcol": false,
      "is_identity": false,
      "is_computed": false,
      "is_filestream": false,
      "is_replicated": false,
      "is_non_sql_subscribed": false,
      "is_merge_published": false,
      "is_dts_replicated": false,
      "is_xml_document": false,
      "xml_collection_id": 0,
      "default_object_id": 0,
      "rule_object_id": 0,
      "is_sparse": false,
      "is_column_set": false,
      "generated_always_type": 0,
      "generated_always_type_desc": "NOT_APPLICABLE",
      "encryption_type": null,
      "encryption_type_desc": null,
      "encryption_algorithm_name": null,
      "column_encryption_key_id": null,
      "column_encryption_key_database_name": null,
      "is_hidden": false,
      "is_masked": false,
      "graph_type": null,
      "graph_type_desc": null
    },
    {
      "schem": "dbo",
      "obj": "aspnet_Membership",
      "type": "Table",
      "name": "Password",
      "system_type_id": 231,
      "user_type_id": 231,
      "max_length": 256,
      "precision": 0,
      "scale": 0,
      "collation_name": "SQL_Latin1_General_CP1_CI_AS",
      "is_nullable": false,
      "is_ansi_padded": true,
      "is_rowguidcol": false,
      "is_identity": false,
      "is_computed": false,
      "is_filestream": false,
      "is_replicated": false,
      "is_non_sql_subscribed": false,
      "is_merge_published": false,
      "is_dts_replicated": false,
      "is_xml_document": false,
      "xml_collection_id": 0,
      "default_object_id": 0,
      "rule_object_id": 0,
      "is_sparse": false,
      "is_column_set": false,
      "generated_always_type": 0,
      "generated_always_type_desc": "NOT_APPLICABLE",
      "encryption_type": null,
      "encryption_type_desc": null,
      "encryption_algorithm_name": null,
      "column_encryption_key_id": null,
      "column_encryption_key_database_name": null,
      "is_hidden": false,
      "is_masked": false,
      "graph_type": null,
      "graph_type_desc": null
    },
    {
      "schem": "dbo",
      "obj": "aspnet_Membership",
      "type": "Table",
      "name": "PasswordFormat",
      "system_type_id": 56,
      "user_type_id": 56,
      "max_length": 4,
      "precision": 10,
      "scale": 0,
      "collation_name": null,
      "is_nullable": false,
      "is_ansi_padded": false,
      "is_rowguidcol": false,
      "is_identity": false,
      "is_computed": false,
      "is_filestream": false,
      "is_replicated": false,
      "is_non_sql_subscribed": false,
      "is_merge_published": false,
      "is_dts_replicated": false,
      "is_xml_document": false,
      "xml_collection_id": 0,
      "default_object_id": 548197003,
      "rule_object_id": 0,
      "is_sparse": false,
      "is_column_set": false,
      "generated_always_type": 0,
      "generated_always_type_desc": "NOT_APPLICABLE",
      "encryption_type": null,
      "encryption_type_desc": null,
      "encryption_algorithm_name": null,
      "column_encryption_key_id": null,
      "column_encryption_key_database_name": null,
      "is_hidden": false,
      "is_masked": false,
      "graph_type": null,
      "graph_type_desc": null
    },
    {
      "schem": "dbo",
      "obj": "aspnet_Membership",
      "type": "Table",
      "name": "PasswordSalt",
      "system_type_id": 231,
      "user_type_id": 231,
      "max_length": 256,
      "precision": 0,
      "scale": 0,
      "collation_name": "SQL_Latin1_General_CP1_CI_AS",
      "is_nullable": false,
      "is_ansi_padded": true,
      "is_rowguidcol": false,
      "is_identity": false,
      "is_computed": false,
      "is_filestream": false,
      "is_replicated": false,
      "is_non_sql_subscribed": false,
      "is_merge_published": false,
      "is_dts_replicated": false,
      "is_xml_document": false,
      "xml_collection_id": 0,
      "default_object_id": 0,
      "rule_object_id": 0,
      "is_sparse": false,
      "is_column_set": false,
      "generated_always_type": 0,
      "generated_always_type_desc": "NOT_APPLICABLE",
      "encryption_type": null,
      "encryption_type_desc": null,
      "encryption_algorithm_name": null,
      "column_encryption_key_id": null,
      "column_encryption_key_database_name": null,
      "is_hidden": false,
      "is_masked": false,
      "graph_type": null,
      "graph_type_desc": null
    },
    {
      "schem": "dbo",
      "obj": "aspnet_Membership",
      "type": "Table",
      "name": "MobilePIN",
      "system_type_id": 231,
      "user_type_id": 231,
      "max_length": 32,
      "precision": 0,
      "scale": 0,
      "collation_name": "SQL_Latin1_General_CP1_CI_AS",
      "is_nullable": true,
      "is_ansi_padded": true,
      "is_rowguidcol": false,
      "is_identity": false,
      "is_computed": false,
      "is_filestream": false,
      "is_replicated": false,
      "is_non_sql_subscribed": false,
      "is_merge_published": false,
      "is_dts_replicated": false,
      "is_xml_document": false,
      "xml_collection_id": 0,
      "default_object_id": 0,
      "rule_object_id": 0,
      "is_sparse": false,
      "is_column_set": false,
      "generated_always_type": 0,
      "generated_always_type_desc": "NOT_APPLICABLE",
      "encryption_type": null,
      "encryption_type_desc": null,
      "encryption_algorithm_name": null,
      "column_encryption_key_id": null,
      "column_encryption_key_database_name": null,
      "is_hidden": false,
      "is_masked": false,
      "graph_type": null,
      "graph_type_desc": null
    },
    {
      "schem": "dbo",
      "obj": "aspnet_Membership",
      "type": "Table",
      "name": "Email",
      "system_type_id": 231,
      "user_type_id": 231,
      "max_length": 512,
      "precision": 0,
      "scale": 0,
      "collation_name": "SQL_Latin1_General_CP1_CI_AS",
      "is_nullable": true,
      "is_ansi_padded": true,
      "is_rowguidcol": false,
      "is_identity": false,
      "is_computed": false,
      "is_filestream": false,
      "is_replicated": false,
      "is_non_sql_subscribed": false,
      "is_merge_published": false,
      "is_dts_replicated": false,
      "is_xml_document": false,
      "xml_collection_id": 0,
      "default_object_id": 0,
      "rule_object_id": 0,
      "is_sparse": false,
      "is_column_set": false,
      "generated_always_type": 0,
      "generated_always_type_desc": "NOT_APPLICABLE",
      "encryption_type": null,
      "encryption_type_desc": null,
      "encryption_algorithm_name": null,
      "column_encryption_key_id": null,
      "column_encryption_key_database_name": null,
      "is_hidden": false,
      "is_masked": false,
      "graph_type": null,
      "graph_type_desc": null
    },
    {
      "schem": "dbo",
      "obj": "aspnet_Membership",
      "type": "Table",
      "name": "LoweredEmail",
      "system_type_id": 231,
      "user_type_id": 231,
      "max_length": 512,
      "precision": 0,
      "scale": 0,
      "collation_name": "SQL_Latin1_General_CP1_CI_AS",
      "is_nullable": true,
      "is_ansi_padded": true,
      "is_rowguidcol": false,
      "is_identity": false,
      "is_computed": false,
      "is_filestream": false,
      "is_replicated": false,
      "is_non_sql_subscribed": false,
      "is_merge_published": false,
      "is_dts_replicated": false,
      "is_xml_document": false,
      "xml_collection_id": 0,
      "default_object_id": 0,
      "rule_object_id": 0,
      "is_sparse": false,
      "is_column_set": false,
      "generated_always_type": 0,
      "generated_always_type_desc": "NOT_APPLICABLE",
      "encryption_type": null,
      "encryption_type_desc": null,
      "encryption_algorithm_name": null,
      "column_encryption_key_id": null,
      "column_encryption_key_database_name": null,
      "is_hidden": false,
      "is_masked": false,
      "graph_type": null,
      "graph_type_desc": null
    },
    {
      "schem": "dbo",
      "obj": "aspnet_Membership",
      "type": "Table",
      "name": "PasswordQuestion",
      "system_type_id": 231,
      "user_type_id": 231,
      "max_length": 512,
      "precision": 0,
      "scale": 0,
      "collation_name": "SQL_Latin1_General_CP1_CI_AS",
      "is_nullable": true,
      "is_ansi_padded": true,
      "is_rowguidcol": false,
      "is_identity": false,
      "is_computed": false,
      "is_filestream": false,
      "is_replicated": false,
      "is_non_sql_subscribed": false,
      "is_merge_published": false,
      "is_dts_replicated": false,
      "is_xml_document": false,
      "xml_collection_id": 0,
      "default_object_id": 0,
      "rule_object_id": 0,
      "is_sparse": false,
      "is_column_set": false,
      "generated_always_type": 0,
      "generated_always_type_desc": "NOT_APPLICABLE",
      "encryption_type": null,
      "encryption_type_desc": null,
      "encryption_algorithm_name": null,
      "column_encryption_key_id": null,
      "column_encryption_key_database_name": null,
      "is_hidden": false,
      "is_masked": false,
      "graph_type": null,
      "graph_type_desc": null
    },
    {
      "schem": "dbo",
      "obj": "aspnet_Membership",
      "type": "Table",
      "name": "PasswordAnswer",
      "system_type_id": 231,
      "user_type_id": 231,
      "max_length": 256,
      "precision": 0,
      "scale": 0,
      "collation_name": "SQL_Latin1_General_CP1_CI_AS",
      "is_nullable": true,
      "is_ansi_padded": true,
      "is_rowguidcol": false,
      "is_identity": false,
      "is_computed": false,
      "is_filestream": false,
      "is_replicated": false,
      "is_non_sql_subscribed": false,
      "is_merge_published": false,
      "is_dts_replicated": false,
      "is_xml_document": false,
      "xml_collection_id": 0,
      "default_object_id": 0,
      "rule_object_id": 0,
      "is_sparse": false,
      "is_column_set": false,
      "generated_always_type": 0,
      "generated_always_type_desc": "NOT_APPLICABLE",
      "encryption_type": null,
      "encryption_type_desc": null,
      "encryption_algorithm_name": null,
      "column_encryption_key_id": null,
      "column_encryption_key_database_name": null,
      "is_hidden": false,
      "is_masked": false,
      "graph_type": null,
      "graph_type_desc": null
    },
    {
      "schem": "dbo",
      "obj": "aspnet_Membership",
      "type": "Table",
      "name": "IsApproved",
      "system_type_id": 104,
      "user_type_id": 104,
      "max_length": 1,
      "precision": 1,
      "scale": 0,
      "collation_name": null,
      "is_nullable": false,
      "is_ansi_padded": false,
      "is_rowguidcol": false,
      "is_identity": false,
      "is_computed": false,
      "is_filestream": false,
      "is_replicated": false,
      "is_non_sql_subscribed": false,
      "is_merge_published": false,
      "is_dts_replicated": false,
      "is_xml_document": false,
      "xml_collection_id": 0,
      "default_object_id": 0,
      "rule_object_id": 0,
      "is_sparse": false,
      "is_column_set": false,
      "generated_always_type": 0,
      "generated_always_type_desc": "NOT_APPLICABLE",
      "encryption_type": null,
      "encryption_type_desc": null,
      "encryption_algorithm_name": null,
      "column_encryption_key_id": null,
      "column_encryption_key_database_name": null,
      "is_hidden": false,
      "is_masked": false,
      "graph_type": null,
      "graph_type_desc": null
    },
    {
      "schem": "dbo",
      "obj": "aspnet_Membership",
      "type": "Table",
      "name": "IsLockedOut",
      "system_type_id": 104,
      "user_type_id": 104,
      "max_length": 1,
      "precision": 1,
      "scale": 0,
      "collation_name": null,
      "is_nullable": false,
      "is_ansi_padded": false,
      "is_rowguidcol": false,
      "is_identity": false,
      "is_computed": false,
      "is_filestream": false,
      "is_replicated": false,
      "is_non_sql_subscribed": false,
      "is_merge_published": false,
      "is_dts_replicated": false,
      "is_xml_document": false,
      "xml_collection_id": 0,
      "default_object_id": 0,
      "rule_object_id": 0,
      "is_sparse": false,
      "is_column_set": false,
      "generated_always_type": 0,
      "generated_always_type_desc": "NOT_APPLICABLE",
      "encryption_type": null,
      "encryption_type_desc": null,
      "encryption_algorithm_name": null,
      "column_encryption_key_id": null,
      "column_encryption_key_database_name": null,
      "is_hidden": false,
      "is_masked": false,
      "graph_type": null,
      "graph_type_desc": null
    },
    {
      "schem": "dbo",
      "obj": "aspnet_Membership",
      "type": "Table",
      "name": "CreateDate",
      "system_type_id": 61,
      "user_type_id": 61,
      "max_length": 8,
      "precision": 23,
      "scale": 3,
      "collation_name": null,
      "is_nullable": false,
      "is_ansi_padded": false,
      "is_rowguidcol": false,
      "is_identity": false,
      "is_computed": false,
      "is_filestream": false,
      "is_replicated": false,
      "is_non_sql_subscribed": false,
      "is_merge_published": false,
      "is_dts_replicated": false,
      "is_xml_document": false,
      "xml_collection_id": 0,
      "default_object_id": 0,
      "rule_object_id": 0,
      "is_sparse": false,
      "is_column_set": false,
      "generated_always_type": 0,
      "generated_always_type_desc": "NOT_APPLICABLE",
      "encryption_type": null,
      "encryption_type_desc": null,
      "encryption_algorithm_name": null,
      "column_encryption_key_id": null,
      "column_encryption_key_database_name": null,
      "is_hidden": false,
      "is_masked": false,
      "graph_type": null,
      "graph_type_desc": null
    },
    {
      "schem": "dbo",
      "obj": "aspnet_Membership",
      "type": "Table",
      "name": "LastLoginDate",
      "system_type_id": 61,
      "user_type_id": 61,
      "max_length": 8,
      "precision": 23,
      "scale": 3,
      "collation_name": null,
      "is_nullable": false,
      "is_ansi_padded": false,
      "is_rowguidcol": false,
      "is_identity": false,
      "is_computed": false,
      "is_filestream": false,
      "is_replicated": false,
      "is_non_sql_subscribed": false,
      "is_merge_published": false,
      "is_dts_replicated": false,
      "is_xml_document": false,
      "xml_collection_id": 0,
      "default_object_id": 0,
      "rule_object_id": 0,
      "is_sparse": false,
      "is_column_set": false,
      "generated_always_type": 0,
      "generated_always_type_desc": "NOT_APPLICABLE",
      "encryption_type": null,
      "encryption_type_desc": null,
      "encryption_algorithm_name": null,
      "column_encryption_key_id": null,
      "column_encryption_key_database_name": null,
      "is_hidden": false,
      "is_masked": false,
      "graph_type": null,
      "graph_type_desc": null
    },
    {
      "schem": "dbo",
      "obj": "aspnet_Membership",
      "type": "Table",
      "name": "LastPasswordChangedDate",
      "system_type_id": 61,
      "user_type_id": 61,
      "max_length": 8,
      "precision": 23,
      "scale": 3,
      "collation_name": null,
      "is_nullable": false,
      "is_ansi_padded": false,
      "is_rowguidcol": false,
      "is_identity": false,
      "is_computed": false,
      "is_filestream": false,
      "is_replicated": false,
      "is_non_sql_subscribed": false,
      "is_merge_published": false,
      "is_dts_replicated": false,
      "is_xml_document": false,
      "xml_collection_id": 0,
      "default_object_id": 0,
      "rule_object_id": 0,
      "is_sparse": false,
      "is_column_set": false,
      "generated_always_type": 0,
      "generated_always_type_desc": "NOT_APPLICABLE",
      "encryption_type": null,
      "encryption_type_desc": null,
      "encryption_algorithm_name": null,
      "column_encryption_key_id": null,
      "column_encryption_key_database_name": null,
      "is_hidden": false,
      "is_masked": false,
      "graph_type": null,
      "graph_type_desc": null
    },
    {
      "schem": "dbo",
      "obj": "aspnet_Membership",
      "type": "Table",
      "name": "LastLockoutDate",
      "system_type_id": 61,
      "user_type_id": 61,
      "max_length": 8,
      "precision": 23,
      "scale": 3,
      "collation_name": null,
      "is_nullable": false,
      "is_ansi_padded": false,
      "is_rowguidcol": false,
      "is_identity": false,
      "is_computed": false,
      "is_filestream": false,
      "is_replicated": false,
      "is_non_sql_subscribed": false,
      "is_merge_published": false,
      "is_dts_replicated": false,
      "is_xml_document": false,
      "xml_collection_id": 0,
      "default_object_id": 0,
      "rule_object_id": 0,
      "is_sparse": false,
      "is_column_set": false,
      "generated_always_type": 0,
      "generated_always_type_desc": "NOT_APPLICABLE",
      "encryption_type": null,
      "encryption_type_desc": null,
      "encryption_algorithm_name": null,
      "column_encryption_key_id": null,
      "column_encryption_key_database_name": null,
      "is_hidden": false,
      "is_masked": false,
      "graph_type": null,
      "graph_type_desc": null
    },
    {
      "schem": "dbo",
      "obj": "aspnet_Membership",
      "type": "Table",
      "name": "FailedPasswordAttemptCount",
      "system_type_id": 56,
      "user_type_id": 56,
      "max_length": 4,
      "precision": 10,
      "scale": 0,
      "collation_name": null,
      "is_nullable": false,
      "is_ansi_padded": false,
      "is_rowguidcol": false,
      "is_identity": false,
      "is_computed": false,
      "is_filestream": false,
      "is_replicated": false,
      "is_non_sql_subscribed": false,
      "is_merge_published": false,
      "is_dts_replicated": false,
      "is_xml_document": false,
      "xml_collection_id": 0,
      "default_object_id": 0,
      "rule_object_id": 0,
      "is_sparse": false,
      "is_column_set": false,
      "generated_always_type": 0,
      "generated_always_type_desc": "NOT_APPLICABLE",
      "encryption_type": null,
      "encryption_type_desc": null,
      "encryption_algorithm_name": null,
      "column_encryption_key_id": null,
      "column_encryption_key_database_name": null,
      "is_hidden": false,
      "is_masked": false,
      "graph_type": null,
      "graph_type_desc": null
    },
    {
      "schem": "dbo",
      "obj": "aspnet_Membership",
      "type": "Table",
      "name": "FailedPasswordAttemptWindowStart",
      "system_type_id": 61,
      "user_type_id": 61,
      "max_length": 8,
      "precision": 23,
      "scale": 3,
      "collation_name": null,
      "is_nullable": false,
      "is_ansi_padded": false,
      "is_rowguidcol": false,
      "is_identity": false,
      "is_computed": false,
      "is_filestream": false,
      "is_replicated": false,
      "is_non_sql_subscribed": false,
      "is_merge_published": false,
      "is_dts_replicated": false,
      "is_xml_document": false,
      "xml_collection_id": 0,
      "default_object_id": 0,
      "rule_object_id": 0,
      "is_sparse": false,
      "is_column_set": false,
      "generated_always_type": 0,
      "generated_always_type_desc": "NOT_APPLICABLE",
      "encryption_type": null,
      "encryption_type_desc": null,
      "encryption_algorithm_name": null,
      "column_encryption_key_id": null,
      "column_encryption_key_database_name": null,
      "is_hidden": false,
      "is_masked": false,
      "graph_type": null,
      "graph_type_desc": null
    },
    {
      "schem": "dbo",
      "obj": "aspnet_Membership",
      "type": "Table",
      "name": "FailedPasswordAnswerAttemptCount",
      "system_type_id": 56,
      "user_type_id": 56,
      "max_length": 4,
      "precision": 10,
      "scale": 0,
      "collation_name": null,
      "is_nullable": false,
      "is_ansi_padded": false,
      "is_rowguidcol": false,
      "is_identity": false,
      "is_computed": false,
      "is_filestream": false,
      "is_replicated": false,
      "is_non_sql_subscribed": false,
      "is_merge_published": false,
      "is_dts_replicated": false,
      "is_xml_document": false,
      "xml_collection_id": 0,
      "default_object_id": 0,
      "rule_object_id": 0,
      "is_sparse": false,
      "is_column_set": false,
      "generated_always_type": 0,
      "generated_always_type_desc": "NOT_APPLICABLE",
      "encryption_type": null,
      "encryption_type_desc": null,
      "encryption_algorithm_name": null,
      "column_encryption_key_id": null,
      "column_encryption_key_database_name": null,
      "is_hidden": false,
      "is_masked": false,
      "graph_type": null,
      "graph_type_desc": null
    },
    {
      "schem": "dbo",
      "obj": "aspnet_Membership",
      "type": "Table",
      "name": "FailedPasswordAnswerAttemptWindowStart",
      "system_type_id": 61,
      "user_type_id": 61,
      "max_length": 8,
      "precision": 23,
      "scale": 3,
      "collation_name": null,
      "is_nullable": false,
      "is_ansi_padded": false,
      "is_rowguidcol": false,
      "is_identity": false,
      "is_computed": false,
      "is_filestream": false,
      "is_replicated": false,
      "is_non_sql_subscribed": false,
      "is_merge_published": false,
      "is_dts_replicated": false,
      "is_xml_document": false,
      "xml_collection_id": 0,
      "default_object_id": 0,
      "rule_object_id": 0,
      "is_sparse": false,
      "is_column_set": false,
      "generated_always_type": 0,
      "generated_always_type_desc": "NOT_APPLICABLE",
      "encryption_type": null,
      "encryption_type_desc": null,
      "encryption_algorithm_name": null,
      "column_encryption_key_id": null,
      "column_encryption_key_database_name": null,
      "is_hidden": false,
      "is_masked": false,
      "graph_type": null,
      "graph_type_desc": null
    },
    {
      "schem": "dbo",
      "obj": "aspnet_Membership",
      "type": "Table",
      "name": "Comment",
      "system_type_id": 99,
      "user_type_id": 99,
      "max_length": 16,
      "precision": 0,
      "scale": 0,
      "collation_name": "SQL_Latin1_General_CP1_CI_AS",
      "is_nullable": true,
      "is_ansi_padded": false,
      "is_rowguidcol": false,
      "is_identity": false,
      "is_computed": false,
      "is_filestream": false,
      "is_replicated": false,
      "is_non_sql_subscribed": false,
      "is_merge_published": false,
      "is_dts_replicated": false,
      "is_xml_document": false,
      "xml_collection_id": 0,
      "default_object_id": 0,
      "rule_object_id": 0,
      "is_sparse": false,
      "is_column_set": false,
      "generated_always_type": 0,
      "generated_always_type_desc": "NOT_APPLICABLE",
      "encryption_type": null,
      "encryption_type_desc": null,
      "encryption_algorithm_name": null,
      "column_encryption_key_id": null,
      "column_encryption_key_database_name": null,
      "is_hidden": false,
      "is_masked": false,
      "graph_type": null,
      "graph_type_desc": null
    }
  ],
  "Foreign keys": [
    {
      "schem": "dbo",
      "obj": "aspnet_Membership",
      "type": "Table",
      "object_id": 1865773704,
      "type_desc": "FOREIGN_KEY_CONSTRAINT",
      "create_date": "2021-07-08T13:16:18.64",
      "modify_date": "2021-07-08T13:16:18.64",
      "is_ms_shipped": false,
      "is_published": false,
      "is_schema_published": false,
      "key_index_id": 4,
      "is_disabled": false,
      "is_not_for_replication": false,
      "is_not_trusted": false,
      "delete_referential_action": 0,
      "delete_referential_action_desc": "NO_ACTION",
      "update_referential_action": 0,
      "update_referential_action_desc": "NO_ACTION",
      "is_system_named": false,
      "column_id": 1,
      "parent_column_id": 1,
      "colname": "ApplicationId",
      "reftable": "aspnet_Applications",
      "fercol": "ApplicationName"
    },
    {
      "schem": "dbo",
      "obj": "aspnet_Membership",
      "type": "Table",
      "object_id": 1881773761,
      "type_desc": "FOREIGN_KEY_CONSTRAINT",
      "create_date": "2021-07-08T13:16:18.643",
      "modify_date": "2021-07-08T13:16:18.643",
      "is_ms_shipped": false,
      "is_published": false,
      "is_schema_published": false,
      "key_index_id": 4,
      "is_disabled": false,
      "is_not_for_replication": false,
      "is_not_trusted": false,
      "delete_referential_action": 0,
      "delete_referential_action_desc": "NO_ACTION",
      "update_referential_action": 0,
      "update_referential_action_desc": "NO_ACTION",
      "is_system_named": false,
      "column_id": 1,
      "parent_column_id": 1,
      "colname": "ApplicationId",
      "reftable": "aspnet_Applications",
      "fercol": "ApplicationName"
    },
    {
      "schem": "dbo",
      "obj": "aspnet_Membership",
      "type": "Table",
      "object_id": 1897773818,
      "type_desc": "FOREIGN_KEY_CONSTRAINT",
      "create_date": "2021-07-08T13:16:18.643",
      "modify_date": "2021-07-08T13:16:18.643",
      "is_ms_shipped": false,
      "is_published": false,
      "is_schema_published": false,
      "key_index_id": 4,
      "is_disabled": false,
      "is_not_for_replication": false,
      "is_not_trusted": false,
      "delete_referential_action": 0,
      "delete_referential_action_desc": "NO_ACTION",
      "update_referential_action": 0,
      "update_referential_action_desc": "NO_ACTION",
      "is_system_named": false,
      "column_id": 1,
      "parent_column_id": 1,
      "colname": "ApplicationId",
      "reftable": "aspnet_Applications",
      "fercol": "ApplicationName"
    },
    {
      "schem": "dbo",
      "obj": "aspnet_Membership",
      "type": "Table",
      "object_id": 1913773875,
      "type_desc": "FOREIGN_KEY_CONSTRAINT",
      "create_date": "2021-07-08T13:16:18.643",
      "modify_date": "2021-07-08T13:16:18.643",
      "is_ms_shipped": false,
      "is_published": false,
      "is_schema_published": false,
      "key_index_id": 4,
      "is_disabled": false,
      "is_not_for_replication": false,
      "is_not_trusted": false,
      "delete_referential_action": 0,
      "delete_referential_action_desc": "NO_ACTION",
      "update_referential_action": 0,
      "update_referential_action_desc": "NO_ACTION",
      "is_system_named": false,
      "column_id": 1,
      "parent_column_id": 1,
      "colname": "ApplicationId",
      "reftable": "aspnet_Applications",
      "fercol": "ApplicationName"
    },
    {
      "schem": "dbo",
      "obj": "aspnet_Membership",
      "type": "Table",
      "object_id": 1929773932,
      "type_desc": "FOREIGN_KEY_CONSTRAINT",
      "create_date": "2021-07-08T13:16:18.647",
      "modify_date": "2021-07-08T13:16:18.647",
      "is_ms_shipped": false,
      "is_published": false,
      "is_schema_published": false,
      "key_index_id": 4,
      "is_disabled": false,
      "is_not_for_replication": false,
      "is_not_trusted": false,
      "delete_referential_action": 0,
      "delete_referential_action_desc": "NO_ACTION",
      "update_referential_action": 0,
      "update_referential_action_desc": "NO_ACTION",
      "is_system_named": false,
      "column_id": 1,
      "parent_column_id": 1,
      "colname": "ApplicationId",
      "reftable": "aspnet_Applications",
      "fercol": "ApplicationName"
    },
    {
      "schem": "dbo",
      "obj": "aspnet_Membership",
      "type": "Table",
      "object_id": 1945773989,
      "type_desc": "FOREIGN_KEY_CONSTRAINT",
      "create_date": "2021-07-08T13:16:18.647",
      "modify_date": "2021-07-08T13:16:18.647",
      "is_ms_shipped": false,
      "is_published": false,
      "is_schema_published": false,
      "key_index_id": 4,
      "is_disabled": false,
      "is_not_for_replication": false,
      "is_not_trusted": false,
      "delete_referential_action": 0,
      "delete_referential_action_desc": "NO_ACTION",
      "update_referential_action": 0,
      "update_referential_action_desc": "NO_ACTION",
      "is_system_named": false,
      "column_id": 1,
      "parent_column_id": 1,
      "colname": "ApplicationId",
      "reftable": "aspnet_Applications",
      "fercol": "ApplicationName"
    },
    {
      "schem": "dbo",
      "obj": "aspnet_Membership",
      "type": "Table",
      "object_id": 1961774046,
      "type_desc": "FOREIGN_KEY_CONSTRAINT",
      "create_date": "2021-07-08T13:16:18.647",
      "modify_date": "2021-07-08T13:16:18.647",
      "is_ms_shipped": false,
      "is_published": false,
      "is_schema_published": false,
      "key_index_id": 2,
      "is_disabled": false,
      "is_not_for_replication": false,
      "is_not_trusted": false,
      "delete_referential_action": 0,
      "delete_referential_action_desc": "NO_ACTION",
      "update_referential_action": 0,
      "update_referential_action_desc": "NO_ACTION",
      "is_system_named": false,
      "column_id": 1,
      "parent_column_id": 2,
      "colname": "ApplicationId",
      "reftable": "aspnet_Users",
      "fercol": "ApplicationId"
    },
    {
      "schem": "dbo",
      "obj": "aspnet_Membership",
      "type": "Table",
      "object_id": 1977774103,
      "type_desc": "FOREIGN_KEY_CONSTRAINT",
      "create_date": "2021-07-08T13:16:18.65",
      "modify_date": "2021-07-08T13:16:18.65",
      "is_ms_shipped": false,
      "is_published": false,
      "is_schema_published": false,
      "key_index_id": 2,
      "is_disabled": false,
      "is_not_for_replication": false,
      "is_not_trusted": false,
      "delete_referential_action": 0,
      "delete_referential_action_desc": "NO_ACTION",
      "update_referential_action": 0,
      "update_referential_action_desc": "NO_ACTION",
      "is_system_named": false,
      "column_id": 1,
      "parent_column_id": 2,
      "colname": "ApplicationId",
      "reftable": "aspnet_Users",
      "fercol": "ApplicationId"
    },
    {
      "schem": "dbo",
      "obj": "aspnet_Membership",
      "type": "Table",
      "object_id": 1993774160,
      "type_desc": "FOREIGN_KEY_CONSTRAINT",
      "create_date": "2021-07-08T13:16:18.65",
      "modify_date": "2021-07-08T13:16:18.65",
      "is_ms_shipped": false,
      "is_published": false,
      "is_schema_published": false,
      "key_index_id": 2,
      "is_disabled": false,
      "is_not_for_replication": false,
      "is_not_trusted": false,
      "delete_referential_action": 0,
      "delete_referential_action_desc": "NO_ACTION",
      "update_referential_action": 0,
      "update_referential_action_desc": "NO_ACTION",
      "is_system_named": false,
      "column_id": 1,
      "parent_column_id": 2,
      "colname": "ApplicationId",
      "reftable": "aspnet_Users",
      "fercol": "ApplicationId"
    },
    {
      "schem": "dbo",
      "obj": "aspnet_Membership",
      "type": "Table",
      "object_id": 2009774217,
      "type_desc": "FOREIGN_KEY_CONSTRAINT",
      "create_date": "2021-07-08T13:16:18.65",
      "modify_date": "2021-07-08T13:16:18.65",
      "is_ms_shipped": false,
      "is_published": false,
      "is_schema_published": false,
      "key_index_id": 2,
      "is_disabled": false,
      "is_not_for_replication": false,
      "is_not_trusted": false,
      "delete_referential_action": 0,
      "delete_referential_action_desc": "NO_ACTION",
      "update_referential_action": 0,
      "update_referential_action_desc": "NO_ACTION",
      "is_system_named": false,
      "column_id": 1,
      "parent_column_id": 2,
      "colname": "ApplicationId",
      "reftable": "aspnet_Users",
      "fercol": "ApplicationId"
    },
    {
      "schem": "dbo",
      "obj": "aspnet_Membership",
      "type": "Table",
      "object_id": 2025774274,
      "type_desc": "FOREIGN_KEY_CONSTRAINT",
      "create_date": "2021-07-08T13:16:18.653",
      "modify_date": "2021-07-08T13:16:18.653",
      "is_ms_shipped": false,
      "is_published": false,
      "is_schema_published": false,
      "key_index_id": 2,
      "is_disabled": false,
      "is_not_for_replication": false,
      "is_not_trusted": false,
      "delete_referential_action": 0,
      "delete_referential_action_desc": "NO_ACTION",
      "update_referential_action": 0,
      "update_referential_action_desc": "NO_ACTION",
      "is_system_named": false,
      "column_id": 1,
      "parent_column_id": 2,
      "colname": "ApplicationId",
      "reftable": "aspnet_Users",
      "fercol": "ApplicationId"
    },
    {
      "schem": "dbo",
      "obj": "aspnet_Membership",
      "type": "Table",
      "object_id": 2041774331,
      "type_desc": "FOREIGN_KEY_CONSTRAINT",
      "create_date": "2021-07-08T13:16:18.653",
      "modify_date": "2021-07-08T13:16:18.653",
      "is_ms_shipped": false,
      "is_published": false,
      "is_schema_published": false,
      "key_index_id": 2,
      "is_disabled": false,
      "is_not_for_replication": false,
      "is_not_trusted": false,
      "delete_referential_action": 0,
      "delete_referential_action_desc": "NO_ACTION",
      "update_referential_action": 0,
      "update_referential_action_desc": "NO_ACTION",
      "is_system_named": false,
      "column_id": 1,
      "parent_column_id": 2,
      "colname": "ApplicationId",
      "reftable": "aspnet_Users",
      "fercol": "ApplicationId"
    }
  ],
  "Check constraints": [],
  "Triggers": []
}